MANIFEST.in
README.rst
setup.py
bin/rosa
rosa/__init__.py
rosa/build_rosinstall.py
rosa/console_script.py
rosa/create_workspace.py
rosa/merge_rosinstall.py
rosa/workspace.py
rosa.egg-info/PKG-INFO
rosa.egg-info/SOURCES.txt
rosa.egg-info/dependency_links.txt
rosa.egg-info/not-zip-safe
rosa.egg-info/top_level.txt