Metadata-Version: 1.0
Name: rosa
Version: 0.1.3
Summary: Helper script for ROS
Home-page: http://github.com/abencz/rosa
Author: Alex Bencz
Author-email: UNKNOWN
License: BSD
Platform: UNKNOWN
